aursad/__init__.py
aursad/aursad.py
aursad/utils.py
aursad-0.2.4.dist-info/LICENSE
aursad-0.2.4.dist-info/METADATA
aursad-0.2.4.dist-info/WHEEL
aursad-0.2.4.dist-info/top_level.txt
aursad-0.2.4.dist-info/RECORD
