Metadata-Version: 2.1
Name: aursad
Version: 0.2.4
Summary: Accompanying library to the AURSAD dataset
Home-page: https://github.com/CptPirx/robo-package
Author: Błażej Leporowski
Author-email: bleporowski@outlook.com
License: UNKNOWN
Platform: UNKNOWN
Classifier: Programming Language :: Python :: 3.6
Classifier: License :: OSI Approved :: MIT License
Classifier: Operating System :: Microsoft :: Windows :: Windows 10
Requires-Python: >=3.6
Requires-Dist: tqdm
Requires-Dist: sklearn
Requires-Dist: numpy
Requires-Dist: pandas
Requires-Dist: tensorflow
